RedisShejiYuShixianDierBan/README.md
RedisShejiYuShixianDierBan/__init__.py
RedisShejiYuShixianDierBan/__main__.py
RedisShejiYuShixianDierBan/file.epub
RedisShejiYuShixianDierBan/index.html
RedisShejiYuShixianDierBan/css/__init__.py
RedisShejiYuShixianDierBan/css/annotations.css
RedisShejiYuShixianDierBan/css/main.css
RedisShejiYuShixianDierBan/css/normalize.css
RedisShejiYuShixianDierBan/css/popup.css
RedisShejiYuShixianDierBan/font/__init__.py
RedisShejiYuShixianDierBan/font/fontello.eot
RedisShejiYuShixianDierBan/font/fontello.svg
RedisShejiYuShixianDierBan/font/fontello.ttf
RedisShejiYuShixianDierBan/font/fontello.woff
RedisShejiYuShixianDierBan/img/__init__.py
RedisShejiYuShixianDierBan/img/annotator-glyph-sprite.png
RedisShejiYuShixianDierBan/img/annotator-icon-sprite.png
RedisShejiYuShixianDierBan/img/apple-touch-icon.png
RedisShejiYuShixianDierBan/img/cancelfullscreen.png
RedisShejiYuShixianDierBan/img/close.png
RedisShejiYuShixianDierBan/img/fullscreen.png
RedisShejiYuShixianDierBan/img/loader.gif
RedisShejiYuShixianDierBan/img/menu-icon.png
RedisShejiYuShixianDierBan/img/save.png
RedisShejiYuShixianDierBan/img/saved.png
RedisShejiYuShixianDierBan/img/settings-s.png
RedisShejiYuShixianDierBan/img/settings.png
RedisShejiYuShixianDierBan/img/star.png
RedisShejiYuShixianDierBan/js/__init__.py
RedisShejiYuShixianDierBan/js/epub.js
RedisShejiYuShixianDierBan/js/epub.min.js
RedisShejiYuShixianDierBan/js/epub.min.map
RedisShejiYuShixianDierBan/js/hooks.min.js
RedisShejiYuShixianDierBan/js/hooks.min.map
RedisShejiYuShixianDierBan/js/reader.js
RedisShejiYuShixianDierBan/js/reader.js.map
RedisShejiYuShixianDierBan/js/reader.min.js
RedisShejiYuShixianDierBan/js/reader.min.map
RedisShejiYuShixianDierBan/js/hooks/__init__.py
RedisShejiYuShixianDierBan/js/hooks/extensions/__init__.py
RedisShejiYuShixianDierBan/js/hooks/extensions/highlight.js
RedisShejiYuShixianDierBan/js/libs/__init__.py
RedisShejiYuShixianDierBan/js/libs/jquery.min.js
redis_sheji_yu_shixian_dier_ban-2024.3.1.0.dist-info/METADATA
redis_sheji_yu_shixian_dier_ban-2024.3.1.0.dist-info/WHEEL
redis_sheji_yu_shixian_dier_ban-2024.3.1.0.dist-info/entry_points.txt
redis_sheji_yu_shixian_dier_ban-2024.3.1.0.dist-info/top_level.txt
redis_sheji_yu_shixian_dier_ban-2024.3.1.0.dist-info/RECORD
